MANIFEST.in
README.md
setup.py
abyss/__init__.py
abyss/settings.py
abyss/urls.py
abyss/wsgi.py
tsuru_dashboard/__init__.py
tsuru_dashboard/settings.py
tsuru_dashboard/urls.py
tsuru_dashboard.egg-info/PKG-INFO
tsuru_dashboard.egg-info/SOURCES.txt
tsuru_dashboard.egg-info/dependency_links.txt
tsuru_dashboard.egg-info/requires.txt
tsuru_dashboard.egg-info/top_level.txt
tsuru_dashboard/admin/__init__.py
tsuru_dashboard/admin/models.py
tsuru_dashboard/admin/urls.py
tsuru_dashboard/admin/views.py
tsuru_dashboard/admin/tests/__init__.py
tsuru_dashboard/admin/tests/test_custom_filters_and_tags.py
tsuru_dashboard/admin/tests/test_deploy_info_view.py
tsuru_dashboard/admin/tests/test_list_deploys_view.py
tsuru_dashboard/admin/tests/test_list_healing_view.py
tsuru_dashboard/admin/tests/test_node_add_view.py
tsuru_dashboard/admin/tests/test_node_info_json_view.py
tsuru_dashboard/admin/tests/test_node_info_view.py
tsuru_dashboard/admin/tests/test_node_remove_view.py
tsuru_dashboard/admin/tests/test_pool_info_view.py
tsuru_dashboard/admin/tests/test_pool_list_view.py
tsuru_dashboard/admin/tests/test_pool_rebalance.py
tsuru_dashboard/admin/tests/test_template_list_json_view.py
tsuru_dashboard/admin/tests/test_urls.py
tsuru_dashboard/apps/__init__.py
tsuru_dashboard/apps/forms.py
tsuru_dashboard/apps/models.py
tsuru_dashboard/apps/urls.py
tsuru_dashboard/apps/views.py
tsuru_dashboard/apps/tests/__init__.py
tsuru_dashboard/apps/tests/test_app_detail_json_view.py
tsuru_dashboard/apps/tests/test_app_info_view.py
tsuru_dashboard/apps/tests/test_app_log_view.py
tsuru_dashboard/apps/tests/test_app_rollback_view.py
tsuru_dashboard/apps/tests/test_app_settings_view.py
tsuru_dashboard/apps/tests/test_create_app_form.py
tsuru_dashboard/apps/tests/test_create_app_view.py
tsuru_dashboard/apps/tests/test_deploy_info_view.py
tsuru_dashboard/apps/tests/test_deploy_list.py
tsuru_dashboard/apps/tests/test_event_info.py
tsuru_dashboard/apps/tests/test_event_list.py
tsuru_dashboard/apps/tests/test_list_app_json_view.py
tsuru_dashboard/apps/tests/test_list_app_view.py
tsuru_dashboard/apps/tests/test_log.py
tsuru_dashboard/apps/tests/test_remove_app_view.py
