Metadata-Version: 1.0
Name: tsuru-dashboard
Version: 0.15.7
Summary: Web dashboard for tsuru PaaS
Home-page: https://github.com/tsuru/tsuru-dashboard
Author: tsuru
Author-email: tsuru@corp.globo.com
License: UNKNOWN
Platform: UNKNOWN
